rura
