Metadata-Version: 2.1
Name: rura
Version: 0.2.3
Summary: Pipelines for machine learning
Home-page: https://github.com/fdabek1/rura
Author: Filip Dabek
License: MIT
Download-URL: https://github.com/fdabek1/rura/archive/0.2.3.tar.gz
Keywords: machine learning,pipeline,etl
Platform: UNKNOWN
Classifier: Development Status :: 3 - Alpha
Classifier: Intended Audience :: Developers
Classifier: Topic :: Software Development :: Build Tools
Classifier: License :: OSI Approved :: MIT License
Classifier: Programming Language :: Python :: 3
Classifier: Programming Language :: Python :: 3.8
Provides-Extra: tests
